{
  "welcomeFile": "comtsmcheadcount/",
  "authenticationMethod": "route",
  "logout": {
    "logoutEndpoint": "/do/logout"
  },
  "routes": [
    {
      "source": "^/hc(.*)$",
      "destination": "mainservice",
      "csrfProtection": false,
      "authenticationType": "none"
    },
    {
      "source": "^/ouadjust(.*)$",
      "destination": "mainservice",
      "csrfProtection": false,
      "authenticationType": "none"
    },
    {
      "source": "^/ou(.*)$",
      "destination": "mainservice",
      "csrfProtection": false,
      "authenticationType": "none"
    },
    {
      "source": "^/period(.*)$",
      "destination": "mainservice",
      "csrfProtection": false,
      "authenticationType": "none"
    },
    {
      "source": "^/excel(.*)$",
      "destination": "mainservice",
      "csrfProtection": false,
      "authenticationType": "none"
    },
    {
      "source": "^/user(.*)$",
      "target": "$1",
      "destination": "user_api"
    }
  ]
}